fourdfpy/__init__.py
fourdfpy-0.0.3.dist-info/LICENSE
fourdfpy-0.0.3.dist-info/METADATA
fourdfpy-0.0.3.dist-info/WHEEL
fourdfpy-0.0.3.dist-info/top_level.txt
fourdfpy-0.0.3.dist-info/RECORD
