Metadata-Version: 2.1
Name: fourdfpy
Version: 0.0.3
Summary: A simple package for converting a 4dfp brain image into a Numpy array.
Author-email: Joey Scanga <joeyscanga92@gmail.com>, Ramone Agard <ramone.agard@gmail.com>
Project-URL: Homepage, https://github.com/washu-seal2/fourdfpy
Project-URL: Issues, https://github.com/washu-seal2/fourdfpy/issues
Classifier: Programming Language :: Python :: 3
Classifier: License :: OSI Approved :: MIT License
Classifier: Operating System :: OS Independent
Requires-Python: >=3.8
License-File: LICENSE
